<?xml version="1.0" encoding="UTF-8"?>
<resources>
  <string name="sunday">неделя</string> 
  <string name="sunday_short">нд</string> 
  <string name="monday">понеделник</string> 
  <string name="monday_short">пн</string> 
  <string name="tuesday">вторник</string> 
  <string name="tuesday_short">вт</string> 
  <string name="wednesday">сряда</string> 
  <string name="wednesday_short">ср</string> 
  <string name="thursday">четвъртък</string> 
  <string name="thursday_short">чт</string> 
  <string name="friday">петък</string> 
  <string name="friday_short">пт</string> 
  <string name="saturday">събота</string> 
  <string name="saturday_short">сб</string>
   
  <string name="jan">януари</string> 
  <string name="feb">февруари</string> 
  <string name="mar">март</string> 
  <string name="apr">април</string> 
  <string name="may">май</string> 
  <string name="jun">юни</string> 
  <string name="jul">юли</string> 
  <string name="aug">август</string> 
  <string name="sep">септември</string> 
  <string name="oct">октомври</string> 
  <string name="nov">ноември</string> 
  <string name="dec">декември</string>
  
  <string name="janRP">януари</string> 
  <string name="febRP">февруари</string> 
  <string name="marRP">март</string> 
  <string name="aprRP">април</string> 
  <string name="mayRP">май</string> 
  <string name="junRP">юни</string> 
  <string name="julRP">юли</string> 
  <string name="augRP">август</string> 
  <string name="sepRP">септември</string> 
  <string name="octRP">октомври</string> 
  <string name="novRP">ноември</string> 
  <string name="decRP">декември</string>
  
   <string name="rightNow">в момента</string>
         
  <string name="oneDay">ден</string> 
  <string name="twoFourDay">дни</string> 
  <string name="fiveDay">дни</string> 	
  
  <string name="oneHour">час</string>
  <string name="twoFourHour">часа</string>
  <string name="fiveHour">часа</string>
   
  <string name="oneMinute">минута</string>
  <string name="twoFourMinute">минути</string>
  <string name="fiveMinute">минути</string>
   
  <string name="daysShort">д</string>
  
  <string name="timeIntervalInFuture">след</string>
  <string name="timeIntervalInPast">преди</string>  
</resources>
